ptthreads/__init__.py
ptthreads/ptthreads.py
ptthreads-0.0.5.dist-info/METADATA
ptthreads-0.0.5.dist-info/WHEEL
ptthreads-0.0.5.dist-info/top_level.txt
ptthreads-0.0.5.dist-info/RECORD
